{
  "timestamp_utc": "2026-05-23T06:21:19Z",
  "class_index": 0,
  "class_name": "not_out",
  "is_out": false,
  "confidence": {
    "not_out": 0.9983135461807251,
    "full": 0.00100774469319731,
    "partial": 0.0006786847370676696
  },
  "weather": {
    "station": "KSEA",
    "visibility_sm": 10.0,
    "ceiling_ft": null,
    "raw": "KSEA 230553Z 36006KT 10SM SCT250 18/09 A2986 RMK AO2 SLP114 T01780094 10250 20172 53001"
  },
  "webcam_url": "https://atmos.uw.edu/data/images/webcam2_latest.jpg",
  "model_version": "latest"
}
