{
  "timestamp_utc": "2026-05-03T12:22:32Z",
  "class_index": 2,
  "class_name": "partial",
  "is_out": true,
  "confidence": {
    "not_out": 0.021934635937213898,
    "full": 0.017372090369462967,
    "partial": 0.9606932401657104
  },
  "weather": {
    "station": "KSEA",
    "visibility_sm": 10.0,
    "ceiling_ft": null,
    "raw": "KSEA 031153Z 02007KT 10SM CLR 14/08 A2995 RMK AO2 SLP146 T01390078 10189 20139 56005 $"
  },
  "webcam_url": "https://atmos.uw.edu/data/images/webcam2_latest.jpg",
  "model_version": "latest"
}
